[
  {
    "description": "",
    "elements": [
      {
        "description": "",
        "id": "menambah-master-tag;menambahkan-tag-baru-di-master-tag",
        "keyword": "Scenario",
        "line": 9,
        "name": "Menambahkan Tag Baru di Master Tag",
        "steps": [
          {
            "arguments": [],
            "keyword": "Given ",
            "line": 10,
            "name": "Login berhasil",
            "match": {
              "location": "steps\\Positive\\B2B\\Master\\Core\\Tag\\tambahMasterTag.steps.js:97"
            },
            "result": {
              "status": "passed",
              "duration": 5487827500
            }
          },
          {
            "arguments": [],
            "keyword": "And ",
            "line": 11,
            "name": "Pergi ke Master",
            "match": {
              "location": "steps\\Positive\\B2B\\Master\\Core\\Tag\\tambahMasterTag.steps.js:128"
            },
            "result": {
              "status": "passed",
              "duration": 492364999
            }
          },
          {
            "arguments": [],
            "keyword": "And ",
            "line": 12,
            "name": "Pergi ke Core",
            "match": {
              "location": "steps\\Positive\\B2B\\Master\\Core\\Tag\\tambahMasterTag.steps.js:132"
            },
            "result": {
              "status": "passed",
              "duration": 54223399
            }
          },
          {
            "arguments": [],
            "keyword": "And ",
            "line": 13,
            "name": "Pergi ke Tag",
            "match": {
              "location": "steps\\Positive\\B2B\\Master\\Core\\Tag\\tambahMasterTag.steps.js:136"
            },
            "result": {
              "status": "passed",
              "duration": 72922999
            }
          },
          {
            "arguments": [],
            "keyword": "When ",
            "line": 14,
            "name": "Saya melihat tampilan list tag",
            "match": {
              "location": "steps\\Positive\\B2B\\Master\\Core\\Tag\\tambahMasterTag.steps.js:142"
            },
            "result": {
              "status": "passed",
              "duration": 1663700
            }
          },
          {
            "arguments": [],
            "keyword": "And ",
            "line": 15,
            "name": "Klik Create New",
            "match": {
              "location": "steps\\Positive\\B2B\\Master\\Core\\Tag\\tambahMasterTag.steps.js:147"
            },
            "result": {
              "status": "passed",
              "duration": 14549646000
            }
          },
          {
            "arguments": [],
            "keyword": "And ",
            "line": 16,
            "name": "Isi datanya",
            "match": {
              "location": "steps\\Positive\\B2B\\Master\\Core\\Tag\\tambahMasterTag.steps.js:155"
            },
            "result": {
              "status": "passed",
              "duration": 11575490000
            }
          },
          {
            "arguments": [],
            "keyword": "Then ",
            "line": 17,
            "name": "Klik Save, dan hasil berhasil",
            "match": {
              "location": "steps\\Positive\\B2B\\Master\\Core\\Tag\\tambahMasterTag.steps.js:180"
            },
            "result": {
              "status": "passed",
              "duration": 9141057699
            }
          }
        ],
        "tags": [
          {
            "name": "@urutan1",
            "line": 6
          }
        ],
        "type": "scenario"
      }
    ],
    "id": "menambah-master-tag",
    "line": 7,
    "keyword": "Feature",
    "name": "Menambah Master Tag",
    "tags": [
      {
        "name": "@urutan1",
        "line": 6
      }
    ],
    "uri": "features\\Positive\\B2B\\Master\\Core\\Tag\\tambahMasterTag.feature"
  },
  {
    "description": "",
    "elements": [
      {
        "description": "",
        "id": "mengedit-master-tag;mengedit-tag-di-master-tag",
        "keyword": "Scenario",
        "line": 9,
        "name": "Mengedit Tag di Master Tag",
        "steps": [
          {
            "arguments": [],
            "keyword": "Given ",
            "line": 10,
            "name": "Login B2B berhasil",
            "match": {
              "location": "steps\\Positive\\B2B\\Master\\Core\\Tag\\editMasterTag.steps.js:66"
            },
            "result": {
              "status": "passed",
              "duration": 5347597699
            }
          },
          {
            "arguments": [],
            "keyword": "And ",
            "line": 11,
            "name": "Master",
            "match": {
              "location": "steps\\Positive\\B2B\\Master\\Core\\Tag\\editMasterTag.steps.js:83"
            },
            "result": {
              "status": "passed",
              "duration": 85349400
            }
          },
          {
            "arguments": [],
            "keyword": "And ",
            "line": 12,
            "name": "Core",
            "match": {
              "location": "steps\\Positive\\B2B\\Master\\Core\\Tag\\editMasterTag.steps.js:87"
            },
            "result": {
              "status": "passed",
              "duration": 71955899
            }
          },
          {
            "arguments": [],
            "keyword": "And ",
            "line": 13,
            "name": "Tag",
            "match": {
              "location": "steps\\Positive\\B2B\\Master\\Core\\Tag\\editMasterTag.steps.js:91"
            },
            "result": {
              "status": "passed",
              "duration": 69003899
            }
          },
          {
            "arguments": [],
            "keyword": "When ",
            "line": 14,
            "name": "Saya melihat tampilan semua list Tag",
            "match": {
              "location": "steps\\Positive\\B2B\\Master\\Core\\Tag\\editMasterTag.steps.js:97"
            },
            "result": {
              "status": "passed",
              "duration": 899199
            }
          },
          {
            "arguments": [],
            "keyword": "And ",
            "line": 15,
            "name": "Cari data yang diinput sebelumnya di excel",
            "match": {
              "location": "steps\\Positive\\B2B\\Master\\Core\\Tag\\editMasterTag.steps.js:101"
            },
            "result": {
              "status": "passed",
              "duration": 13552416100
            }
          },
          {
            "arguments": [],
            "keyword": "And ",
            "line": 16,
            "name": "Klik datanya",
            "match": {
              "location": "steps\\Positive\\B2B\\Master\\Core\\Tag\\editMasterTag.steps.js:109"
            },
            "result": {
              "status": "passed",
              "duration": 1007640299
            }
          },
          {
            "arguments": [],
            "keyword": "And ",
            "line": 17,
            "name": "Klik Edit",
            "match": {
              "location": "steps\\Positive\\B2B\\Master\\Core\\Tag\\editMasterTag.steps.js:114"
            },
            "result": {
              "status": "passed",
              "duration": 20293971899
            }
          },
          {
            "arguments": [],
            "keyword": "And ",
            "line": 18,
            "name": "Isi Data yang mau dirubah",
            "match": {
              "location": "steps\\Positive\\B2B\\Master\\Core\\Tag\\editMasterTag.steps.js:120"
            },
            "result": {
              "status": "passed",
              "duration": 178286399
            }
          },
          {
            "arguments": [],
            "keyword": "Then ",
            "line": 19,
            "name": "Klik Save, dan hasil berhasil di edit",
            "match": {
              "location": "steps\\Positive\\B2B\\Master\\Core\\Tag\\editMasterTag.steps.js:128"
            },
            "result": {
              "status": "failed",
              "duration": 326183550799,
              "error_message": "page.waitForSelector: Target page, context or browser has been closed\nCall log:\n\u001b[2m  - waiting for locator('.loading-indicator') to be hidden\u001b[22m\n\u001b[2m    637 × locator resolved to visible <div _ngcontent-gle-c167=\"\" class=\"loading-indicator\">…</div>\u001b[22m\n\n    at World.<anonymous> (C:\\Users\\kurni\\playwright-cucumber\\steps\\Positive\\B2B\\Master\\Core\\Tag\\editMasterTag.steps.js:131:14)"
            }
          }
        ],
        "tags": [
          {
            "name": "@urutan2",
            "line": 6
          }
        ],
        "type": "scenario"
      }
    ],
    "id": "mengedit-master-tag",
    "line": 7,
    "keyword": "Feature",
    "name": "Mengedit Master Tag",
    "tags": [
      {
        "name": "@urutan2",
        "line": 6
      }
    ],
    "uri": "features\\Positive\\B2B\\Master\\Core\\Tag\\editMasterTag.feature"
  },
  {
    "description": "",
    "elements": [
      {
        "description": "",
        "id": "menghapus-master-tag;menghapus-tag-di-master-tag",
        "keyword": "Scenario",
        "line": 9,
        "name": "Menghapus Tag di Master Tag",
        "steps": [
          {
            "arguments": [],
            "keyword": "Given ",
            "line": 10,
            "name": "Login ke B2B berhasil",
            "match": {
              "location": "steps\\Positive\\B2B\\Master\\Core\\Tag\\hapusMasterTag.steps.js:36"
            },
            "result": {
              "status": "passed",
              "duration": 10084719299
            }
          },
          {
            "arguments": [],
            "keyword": "And ",
            "line": 11,
            "name": "menu Master",
            "match": {
              "location": "steps\\Positive\\B2B\\Master\\Core\\Tag\\hapusMasterTag.steps.js:53"
            },
            "result": {
              "status": "passed",
              "duration": 73071799
            }
          },
          {
            "arguments": [],
            "keyword": "And ",
            "line": 12,
            "name": "menu Core",
            "match": {
              "location": "steps\\Positive\\B2B\\Master\\Core\\Tag\\hapusMasterTag.steps.js:57"
            },
            "result": {
              "status": "passed",
              "duration": 49481000
            }
          },
          {
            "arguments": [],
            "keyword": "And ",
            "line": 13,
            "name": "menu Tag",
            "match": {
              "location": "steps\\Positive\\B2B\\Master\\Core\\Tag\\hapusMasterTag.steps.js:61"
            },
            "result": {
              "status": "passed",
              "duration": 56240600
            }
          },
          {
            "arguments": [],
            "keyword": "When ",
            "line": 14,
            "name": "Saya lihat tampilan semua list Tag",
            "match": {
              "location": "steps\\Positive\\B2B\\Master\\Core\\Tag\\hapusMasterTag.steps.js:67"
            },
            "result": {
              "status": "passed",
              "duration": 939599
            }
          },
          {
            "arguments": [],
            "keyword": "And ",
            "line": 15,
            "name": "Cari data yang diinput sebelumnya",
            "match": {
              "location": "steps\\Positive\\B2B\\Master\\Core\\Tag\\hapusMasterTag.steps.js:71"
            },
            "result": {
              "status": "passed",
              "duration": 14615548000
            }
          },
          {
            "arguments": [],
            "keyword": "And ",
            "line": 16,
            "name": "Klik data tersebut",
            "match": {
              "location": "steps\\Positive\\B2B\\Master\\Core\\Tag\\hapusMasterTag.steps.js:79"
            },
            "result": {
              "status": "passed",
              "duration": 1510751300
            }
          },
          {
            "arguments": [],
            "keyword": "And ",
            "line": 17,
            "name": "Klik Hapus",
            "match": {
              "location": "steps\\Positive\\B2B\\Master\\Core\\Tag\\hapusMasterTag.steps.js:84"
            },
            "result": {
              "status": "passed",
              "duration": 8893781100
            }
          },
          {
            "arguments": [],
            "keyword": "And ",
            "line": 18,
            "name": "Isi Alasannya",
            "match": {
              "location": "steps\\Positive\\B2B\\Master\\Core\\Tag\\hapusMasterTag.steps.js:90"
            },
            "result": {
              "status": "passed",
              "duration": 431549999
            }
          },
          {
            "arguments": [],
            "keyword": "Then ",
            "line": 19,
            "name": "Klik Hapus, dan hasil berhasil di hapus",
            "match": {
              "location": "steps\\Positive\\B2B\\Master\\Core\\Tag\\hapusMasterTag.steps.js:97"
            },
            "result": {
              "status": "passed",
              "duration": 75580399
            }
          }
        ],
        "tags": [
          {
            "name": "@urutan3",
            "line": 6
          }
        ],
        "type": "scenario"
      }
    ],
    "id": "menghapus-master-tag",
    "line": 7,
    "keyword": "Feature",
    "name": "Menghapus Master Tag",
    "tags": [
      {
        "name": "@urutan3",
        "line": 6
      }
    ],
    "uri": "features\\Positive\\B2B\\Master\\Core\\Tag\\hapusMasterTag.feature"
  }
]